odoo/addons/ddmrp_include_location_final/README.rst
odoo/addons/ddmrp_include_location_final/__init__.py
odoo/addons/ddmrp_include_location_final/__manifest__.py
odoo/addons/ddmrp_include_location_final/i18n/ddmrp_include_location_final.pot
odoo/addons/ddmrp_include_location_final/i18n/it.po
odoo/addons/ddmrp_include_location_final/models/__init__.py
odoo/addons/ddmrp_include_location_final/models/stock_buffer.py
odoo/addons/ddmrp_include_location_final/readme/CONTRIBUTORS.md
odoo/addons/ddmrp_include_location_final/readme/DESCRIPTION.md
odoo/addons/ddmrp_include_location_final/static/description/icon.png
odoo/addons/ddmrp_include_location_final/static/description/index.html
odoo/addons/ddmrp_include_location_final/tests/__init__.py
odoo/addons/ddmrp_include_location_final/tests/test_ddmrp_include_location_final.py
odoo_addon_ddmrp_include_location_final-17.0.1.0.0.4.dist-info/METADATA
odoo_addon_ddmrp_include_location_final-17.0.1.0.0.4.dist-info/WHEEL
odoo_addon_ddmrp_include_location_final-17.0.1.0.0.4.dist-info/top_level.txt
odoo_addon_ddmrp_include_location_final-17.0.1.0.0.4.dist-info/RECORD
