Metadata-Version: 2.1
Name: odoo-addon-ddmrp_include_location_final
Version: 17.0.1.0.0.4
Requires-Python: >=3.10
Requires-Dist: odoo-addon-ddmrp>=17.0dev,<17.1dev
Requires-Dist: odoo-addon-stock_push_delay>=17.0dev,<17.1dev
Requires-Dist: odoo>=17.0a,<17.1dev
Summary: This module implements the final location logic of v18 added in v17 by stock_push_delay to DDMRP logic.
Home-page: https://github.com/OCA/ddmrp
License: LGPL-3
Author: ForgeFlow, Odoo Community Association (OCA)
Author-email: support@odoo-community.org
Classifier: Programming Language :: Python
Classifier: Framework :: Odoo
Classifier: Framework :: Odoo :: 17.0
Classifier: License :: OSI Approved :: GNU Lesser General Public License v3 (LGPLv3)
Classifier: Development Status :: 4 - Beta
